dataservices/__init__.py
dataservices/amsterdam_schema/__init__.py
dataservices-0.0.3.dist-info/METADATA
dataservices-0.0.3.dist-info/WHEEL
dataservices-0.0.3.dist-info/top_level.txt
dataservices-0.0.3.dist-info/RECORD
