Metadata-Version: 2.1
Name: dataservices
Version: 0.0.3
Summary: UNKNOWN
Home-page: UNKNOWN
License: UNKNOWN
Platform: UNKNOWN
Requires-Python: >=3.6
Provides-Extra: testing
Requires-Dist: pytest ; extra == 'testing'
Requires-Dist: pylint ; extra == 'testing'
Requires-Dist: flake8 ; extra == 'testing'
